monkdb/client/__init__.py
monkdb/client/_version_standard.py
monkdb/client/data_converter.py
monkdb/client/db_cursor.py
monkdb/client/db_cxn.py
monkdb/client/exceptions.py
monkdb/client/http_connections.py
monkdb/client/objects.py
monkdb/testing/__init__.py
monkdb/testing/layer.py
monkdb/testing/util.py
monkdb-1.0.5.dist-info/LICENSE
monkdb-1.0.5.dist-info/METADATA
monkdb-1.0.5.dist-info/WHEEL
monkdb-1.0.5.dist-info/RECORD
